agentds/__init__.py
agentds/auth.py
agentds/cli.py
agentds/client.py
agentds/config.py
agentds/exceptions.py
agentds/task.py
agentds/types.py
agentds/examples/__init__.py
agentds/examples/basic_client.py
agentds/examples/dataset_example.py
agentds/utils/__init__.py
agentds/utils/validators.py
agentds_bench-1.3.0.dist-info/licenses/LICENSE
agentds_bench-1.3.0.dist-info/METADATA
agentds_bench-1.3.0.dist-info/WHEEL
agentds_bench-1.3.0.dist-info/entry_points.txt
agentds_bench-1.3.0.dist-info/top_level.txt
agentds_bench-1.3.0.dist-info/RECORD
