Metadata-Version: 2.4
Name: agentds-bench
Version: 1.3.0
Summary: Python client for AgentDS-Bench: A streamlined benchmarking platform for evaluating AI agent capabilities in data science tasks
Author-email: AgentDS Team <contact@agentds.org>
Maintainer-email: AgentDS Team <contact@agentds.org>
License-Expression: MIT
Project-URL: Homepage, https://agentds.org
Project-URL: Documentation, https://agentds.org/docs
Project-URL: Repository, https://github.com/agentds/agentds-bench
Project-URL: Bug Tracker, https://github.com/agentds/agentds-bench/issues
Project-URL: Changelog, https://github.com/agentds/agentds-bench/blob/main/CHANGELOG.md
Keywords: artificial-intelligence,benchmarking,data-science,machine-learning,evaluation,agents
Classifier: Development Status :: 5 - Production/Stable
Classifier: Intended Audience :: Developers
Classifier: Intended Audience :: Science/Research
Classifier: Operating System :: OS Independent
Classifier: Programming Language :: Python :: 3
Classifier: Programming Language :: Python :: 3.8
Classifier: Programming Language :: Python :: 3.9
Classifier: Programming Language :: Python :: 3.10
Classifier: Programming Language :: Python :: 3.11
Classifier: Programming Language :: Python :: 3.12
Classifier: Topic :: Scientific/Engineering :: Artificial Intelligence
Classifier: Topic :: Software Development :: Libraries :: Python Modules
Classifier: Topic :: System :: Benchmark
Requires-Python: >=3.8
License-File: LICENSE
Requires-Dist: requests>=2.31.0
Requires-Dist: pandas>=1.3.0
Requires-Dist: python-dotenv>=0.15.0
Provides-Extra: dev
Requires-Dist: pytest>=7.0.0; extra == "dev"
Requires-Dist: pytest-cov>=4.0.0; extra == "dev"
Requires-Dist: black>=22.0.0; extra == "dev"
Requires-Dist: flake8>=4.0.0; extra == "dev"
Requires-Dist: mypy>=0.910; extra == "dev"
Requires-Dist: build>=0.8.0; extra == "dev"
Requires-Dist: twine>=4.0.0; extra == "dev"
Provides-Extra: examples
Requires-Dist: jupyter>=1.0.0; extra == "examples"
Requires-Dist: matplotlib>=3.5.0; extra == "examples"
Requires-Dist: seaborn>=0.11.0; extra == "examples"
Requires-Dist: scikit-learn>=1.0.0; extra == "examples"
Dynamic: license-file
